PyQWebWindow/EventListener.py
PyQWebWindow/QAppManager.py
PyQWebWindow/QArgv.py
PyQWebWindow/QContextMenu.py
PyQWebWindow/QWebWindow.py
PyQWebWindow/QWorker.py
PyQWebWindow/__init__.py
PyQWebWindow/all.py
PyQWebWindow/MqIpc/__init__.py
PyQWebWindow/MqIpc/client.py
PyQWebWindow/MqIpc/server.py
PyQWebWindow/QIpc/__init__.py
PyQWebWindow/QIpc/client.py
PyQWebWindow/QIpc/server.py
PyQWebWindow/controllers/Backend.py
PyQWebWindow/controllers/BindingController.py
PyQWebWindow/controllers/WebViewController.py
PyQWebWindow/controllers/WindowController.py
PyQWebWindow/controllers/__init__.py
PyQWebWindow/utils/EventEmitter.py
PyQWebWindow/utils/Serializable.py
PyQWebWindow/utils/Serializer.py
PyQWebWindow/utils/__init__.py
PyQWebWindow/utils/get_caller_file_abs_path.py
PyQWebWindow/utils/scripts.py
pyqwebwindow-0.6.9.dist-info/licenses/LICENSE
pyqwebwindow-0.6.9.dist-info/METADATA
pyqwebwindow-0.6.9.dist-info/WHEEL
pyqwebwindow-0.6.9.dist-info/top_level.txt
pyqwebwindow-0.6.9.dist-info/RECORD
