Metadata-Version: 2.4
Name: PyQWebWindow
Version: 0.6.9
Summary: Another way to build Python webview GUI applications.
Author-email: BHznJNs <bhznjns@qq.com>
License-Expression: Apache-2.0
Project-URL: Homepage, https://github.com/BHznJNs/PyQWebWindow
Project-URL: Issues, https://github.com/BHznJNs/PyQWebWindow/issues
Classifier: Programming Language :: Python :: 3
Classifier: Operating System :: OS Independent
Requires-Python: >=3.8
License-File: LICENSE
Requires-Dist: PySide6==6.9.1
Requires-Dist: pyzmq==26.4.0
Dynamic: license-file
